{
  "$schema": "https://schema.tauri.app/config/2/capabilities",
  "identifier": "default",
  "description": "Default capabilities for the main window",
  "windows": ["main"],
  "permissions": [
    "core:default",
    "core:window:allow-minimize",
    "core:window:allow-maximize",
    "core:window:allow-unmaximize",
    "core:window:allow-close",
    "core:window:allow-set-title",
    "core:window:allow-start-dragging",
    "core:app:allow-version",
    "core:app:allow-name",
    "core:path:default",
    "dialog:allow-open",
    "dialog:allow-save",
    "dialog:allow-message",
    "dialog:allow-ask",
    "dialog:allow-confirm",
    "fs:allow-read-file",
    "fs:allow-write-file",
    "fs:allow-read-dir",
    "fs:allow-exists",
    "fs:allow-mkdir",
    "fs:allow-remove",
    "fs:allow-rename",
    "fs:allow-copy-file",
    "shell:allow-open"
  ]
}
